{"cameraMode":{"drawMode":0,"name":"Shaded","section":"Shading Mode"},"sceneLighting":false,"audioPlay":false,"sceneViewState":{"m_AlwaysRefresh":false,"showFog":true,"showSkybox":false,"showFlares":true,"showImageEffects":true,"showParticleSystems":true,"showVisualEffectGraphs":true,"m_FxEnabled":true},"in2DMode":false,"pivot":{"x":3.7227747440338136,"y":-4.6477437019348148,"z":2.402555227279663},"rotation":{"x":-0.4370992183685303,"y":-0.3815925419330597,"z":0.21165253221988679,"w":-0.7866766452789307},"size":10.0,"orthographic":false}